LICENSE
README.md
setup.py
yahoo_finance_scraper/__init__.py
yahoo_finance_scraper.egg-info/PKG-INFO
yahoo_finance_scraper.egg-info/SOURCES.txt
yahoo_finance_scraper.egg-info/dependency_links.txt
yahoo_finance_scraper.egg-info/requires.txt
yahoo_finance_scraper.egg-info/top_level.txt