Metadata-Version: 2.1
Name: yahoo-finance-scraper
Version: 1.0.1
Summary: A python library to scrape stock, stock price, stock changes and historical data of company in yahoo finance
Home-page: UNKNOWN
Author: DataKund
Author-email: datakund@gmail.com
License: Apache License 2.0
Keywords: yahoo finance python bot_studio automation scraper stock stock_prices stock_changes historical_data
Platform: UNKNOWN
License-File: LICENSE
